[{"artist":"McCoy Tyner","track":"Contemporary Focus","album_name":"Today And Tomorrow","album_type":"Album","album_date":"1964","album_tracks":"Contemporary Focus (08:28)\/A Night In Tunisia (05:07)\/T 'N' A Blues (04:05)\/Autumn Leaves (06:10)\/Three Flowers (10:11)\/When Sunny Gets Blue (04:42","album_pic":"https:\/\/i.scdn.co\/image\/ab67616d00001e02e2ad553a9862224408dedf0b","genres":"Jazz\/Hard Bop\/Bebop\/Cool Jazz\/Free Jazz","maiuscule":"T"},{"artist":"McCoy Tyner","track":"Passion Dance","album_name":"The Real McCoy (Remastered \/ Rudy Van Gelder Edition)","album_type":"Album","album_date":"1967","album_tracks":"Passion Dance (08:47)\/Contemplation (09:12)\/Four By Five (06:37)\/Search For Peace (06:32)\/Blues On The Corner (06:00","album_pic":"https:\/\/i.scdn.co\/image\/ab67616d00001e0275d3c6d8ab982f6ffc94a10d","genres":"Jazz\/Hard Bop\/Bebop\/Cool Jazz\/Free Jazz","maiuscule":"T"},{"artist":"McCoy Tyner","track":"Contemplation","album_name":"The Real McCoy (Remastered \/ Rudy Van Gelder Edition)","album_type":"Album","album_date":"1967","album_tracks":"Passion Dance (08:47)\/Contemplation (09:12)\/Four By Five (06:37)\/Search For Peace (06:32)\/Blues On The Corner (06:00","album_pic":"https:\/\/i.scdn.co\/image\/ab67616d00001e0275d3c6d8ab982f6ffc94a10d","genres":"Jazz\/Hard Bop\/Bebop\/Cool Jazz\/Free Jazz","maiuscule":"T"},{"artist":"McCoy Tyner","track":"Four By Five","album_name":"The Real McCoy (Remastered \/ Rudy Van Gelder Edition)","album_type":"Album","album_date":"1967","album_tracks":"Passion Dance (08:47)\/Contemplation (09:12)\/Four By Five (06:37)\/Search For Peace (06:32)\/Blues On The Corner (06:00","album_pic":"https:\/\/i.scdn.co\/image\/ab67616d00001e0275d3c6d8ab982f6ffc94a10d","genres":"Jazz\/Hard Bop\/Bebop\/Cool Jazz\/Free Jazz","maiuscule":"T"},{"artist":"McCoy Tyner","track":"Search For Peace","album_name":"The Real McCoy (Remastered \/ Rudy Van Gelder Edition)","album_type":"Album","album_date":"1967","album_tracks":"Passion Dance (08:47)\/Contemplation (09:12)\/Four By Five (06:37)\/Search For Peace (06:32)\/Blues On The Corner (06:00","album_pic":"https:\/\/i.scdn.co\/image\/ab67616d00001e0275d3c6d8ab982f6ffc94a10d","genres":"Jazz\/Hard Bop\/Bebop\/Cool Jazz\/Free Jazz","maiuscule":"T"},{"artist":"McCoy Tyner","track":"Blues On The Corner","album_name":"The Real McCoy (Remastered \/ Rudy Van Gelder Edition)","album_type":"Album","album_date":"1967","album_tracks":"Passion Dance (08:47)\/Contemplation (09:12)\/Four By Five (06:37)\/Search For Peace (06:32)\/Blues On The Corner (06:00","album_pic":"https:\/\/i.scdn.co\/image\/ab67616d00001e0275d3c6d8ab982f6ffc94a10d","genres":"Jazz\/Hard Bop\/Bebop\/Cool Jazz\/Free Jazz","maiuscule":"T"}]