[{"artist":"Kaleidoscope","track":"Egyptian Garden","album_name":"Side Trips (Expanded Edition)","album_type":"Album","album_date":"1967-06-01","album_tracks":"Egyptian Garden (03:06)\/If the Night (01:47)\/Hesitation Blues (02:28)\/Please (03:19)\/Keep Your Mind Open (02:18)\/Pulsating Dream (01:57)\/Oh Death (03:27)\/Come On In (02:08)\/Why Try (03:40)\/Minnie the Moocher (02:16)\/Elevator Man - Single Version (02:56)\/Little Orphan Nannie - Single Version (01:57","album_pic":"https:\/\/i.scdn.co\/image\/ab67616d00001e02eb380bc3c0d017e9a71eb33b","genres":"Psychedelic Rock\/Acid Rock\/Psychedelic Pop","count":14,"maiuscule":"K"},{"artist":"Kaleidoscope","track":"If the Night","album_name":"Side Trips (Expanded Edition)","album_type":"Album","album_date":"1967-06-01","album_tracks":"Egyptian Garden (03:06)\/If the Night (01:47)\/Hesitation Blues (02:28)\/Please (03:19)\/Keep Your Mind Open (02:18)\/Pulsating Dream (01:57)\/Oh Death (03:27)\/Come On In (02:08)\/Why Try (03:40)\/Minnie the Moocher (02:16)\/Elevator Man - Single Version (02:56)\/Little Orphan Nannie - Single Version (01:57","album_pic":"https:\/\/i.scdn.co\/image\/ab67616d00001e02eb380bc3c0d017e9a71eb33b","genres":"Psychedelic Rock\/Acid Rock\/Psychedelic Pop","count":14,"maiuscule":"K"},{"artist":"Kaleidoscope","track":"Hesitation Blues","album_name":"Side Trips (Expanded Edition)","album_type":"Album","album_date":"1967-06-01","album_tracks":"Egyptian Garden (03:06)\/If the Night (01:47)\/Hesitation Blues (02:28)\/Please (03:19)\/Keep Your Mind Open (02:18)\/Pulsating Dream (01:57)\/Oh Death (03:27)\/Come On In (02:08)\/Why Try (03:40)\/Minnie the Moocher (02:16)\/Elevator Man - Single Version (02:56)\/Little Orphan Nannie - Single Version (01:57","album_pic":"https:\/\/i.scdn.co\/image\/ab67616d00001e02eb380bc3c0d017e9a71eb33b","genres":"Psychedelic Rock\/Acid Rock\/Psychedelic Pop","count":14,"maiuscule":"K"},{"artist":"Kaleidoscope","track":"Keep Your Mind Open","album_name":"Side Trips (Expanded Edition)","album_type":"Album","album_date":"1967-06-01","album_tracks":"Egyptian Garden (03:06)\/If the Night (01:47)\/Hesitation Blues (02:28)\/Please (03:19)\/Keep Your Mind Open (02:18)\/Pulsating Dream (01:57)\/Oh Death (03:27)\/Come On In (02:08)\/Why Try (03:40)\/Minnie the Moocher (02:16)\/Elevator Man - Single Version (02:56)\/Little Orphan Nannie - Single Version (01:57","album_pic":"https:\/\/i.scdn.co\/image\/ab67616d00001e02eb380bc3c0d017e9a71eb33b","genres":"Psychedelic Rock\/Acid Rock\/Psychedelic Pop","count":14,"maiuscule":"K"},{"artist":"Kaleidoscope","track":"Pulsating Dream","album_name":"Side Trips (Expanded Edition)","album_type":"Album","album_date":"1967-06-01","album_tracks":"Egyptian Garden (03:06)\/If the Night (01:47)\/Hesitation Blues (02:28)\/Please (03:19)\/Keep Your Mind Open (02:18)\/Pulsating Dream (01:57)\/Oh Death (03:27)\/Come On In (02:08)\/Why Try (03:40)\/Minnie the Moocher (02:16)\/Elevator Man - Single Version (02:56)\/Little Orphan Nannie - Single Version (01:57","album_pic":"https:\/\/i.scdn.co\/image\/ab67616d00001e02eb380bc3c0d017e9a71eb33b","genres":"Psychedelic Rock\/Acid Rock\/Psychedelic Pop","count":14,"maiuscule":"K"},{"artist":"Kaleidoscope","track":"Oh Death","album_name":"Side Trips (Expanded Edition)","album_type":"Album","album_date":"1967-06-01","album_tracks":"Egyptian Garden (03:06)\/If the Night (01:47)\/Hesitation Blues (02:28)\/Please (03:19)\/Keep Your Mind Open (02:18)\/Pulsating Dream (01:57)\/Oh Death (03:27)\/Come On In (02:08)\/Why Try (03:40)\/Minnie the Moocher (02:16)\/Elevator Man - Single Version (02:56)\/Little Orphan Nannie - Single Version (01:57","album_pic":"https:\/\/i.scdn.co\/image\/ab67616d00001e02eb380bc3c0d017e9a71eb33b","genres":"Psychedelic Rock\/Acid Rock\/Psychedelic Pop","count":14,"maiuscule":"K"},{"artist":"Kaleidoscope","track":"Come On In","album_name":"Side Trips (Expanded Edition)","album_type":"Album","album_date":"1967-06-01","album_tracks":"Egyptian Garden (03:06)\/If the Night (01:47)\/Hesitation Blues (02:28)\/Please (03:19)\/Keep Your Mind Open (02:18)\/Pulsating Dream (01:57)\/Oh Death (03:27)\/Come On In (02:08)\/Why Try (03:40)\/Minnie the Moocher (02:16)\/Elevator Man - Single Version (02:56)\/Little Orphan Nannie - Single Version (01:57","album_pic":"https:\/\/i.scdn.co\/image\/ab67616d00001e02eb380bc3c0d017e9a71eb33b","genres":"Psychedelic Rock\/Acid Rock\/Psychedelic Pop","count":14,"maiuscule":"K"},{"artist":"Kaleidoscope","track":"Why Try","album_name":"Side Trips (Expanded Edition)","album_type":"Album","album_date":"1967-06-01","album_tracks":"Egyptian Garden (03:06)\/If the Night (01:47)\/Hesitation Blues (02:28)\/Please (03:19)\/Keep Your Mind Open (02:18)\/Pulsating Dream (01:57)\/Oh Death (03:27)\/Come On In (02:08)\/Why Try (03:40)\/Minnie the Moocher (02:16)\/Elevator Man - Single Version (02:56)\/Little Orphan Nannie - Single Version (01:57","album_pic":"https:\/\/i.scdn.co\/image\/ab67616d00001e02eb380bc3c0d017e9a71eb33b","genres":"Psychedelic Rock\/Acid Rock\/Psychedelic Pop","count":14,"maiuscule":"K"},{"artist":"Kaleidoscope","track":"Minnie the Moocher","album_name":"Side Trips (Expanded Edition)","album_type":"Album","album_date":"1967-06-01","album_tracks":"Egyptian Garden (03:06)\/If the Night (01:47)\/Hesitation Blues (02:28)\/Please (03:19)\/Keep Your Mind Open (02:18)\/Pulsating Dream (01:57)\/Oh Death (03:27)\/Come On In (02:08)\/Why Try (03:40)\/Minnie the Moocher (02:16)\/Elevator Man - Single Version (02:56)\/Little Orphan Nannie - Single Version (01:57","album_pic":"https:\/\/i.scdn.co\/image\/ab67616d00001e02eb380bc3c0d017e9a71eb33b","genres":"Psychedelic Rock\/Acid Rock\/Psychedelic Pop","count":14,"maiuscule":"K"},{"artist":"Kaleidoscope","track":"Elevator Man - Single Version","album_name":"Side Trips (Expanded Edition)","album_type":"Album","album_date":"1967-06-01","album_tracks":"Egyptian Garden (03:06)\/If the Night (01:47)\/Hesitation Blues (02:28)\/Please (03:19)\/Keep Your Mind Open (02:18)\/Pulsating Dream (01:57)\/Oh Death (03:27)\/Come On In (02:08)\/Why Try (03:40)\/Minnie the Moocher (02:16)\/Elevator Man - Single Version (02:56)\/Little Orphan Nannie - Single Version (01:57","album_pic":"https:\/\/i.scdn.co\/image\/ab67616d00001e02eb380bc3c0d017e9a71eb33b","genres":"Psychedelic Rock\/Acid Rock\/Psychedelic Pop","count":14,"maiuscule":"K"},{"artist":"Kaleidoscope","track":"Little Orphan Nannie - Single Version","album_name":"Side Trips (Expanded Edition)","album_type":"Album","album_date":"1967-06-01","album_tracks":"Egyptian Garden (03:06)\/If the Night (01:47)\/Hesitation Blues (02:28)\/Please (03:19)\/Keep Your Mind Open (02:18)\/Pulsating Dream (01:57)\/Oh Death (03:27)\/Come On In (02:08)\/Why Try (03:40)\/Minnie the Moocher (02:16)\/Elevator Man - Single Version (02:56)\/Little Orphan Nannie - Single Version (01:57","album_pic":"https:\/\/i.scdn.co\/image\/ab67616d00001e02eb380bc3c0d017e9a71eb33b","genres":"Psychedelic Rock\/Acid Rock\/Psychedelic Pop","count":14,"maiuscule":"K"},{"artist":"Kaleidoscope","track":"I Found Out","album_name":"A Beacon From Mars (Expanded Edition)","album_type":"Album","album_date":"1968-06-01","album_tracks":"I Found Out (02:10)\/Greenwood Sidee (04:16)\/Life Will Pass You By (03:25)\/Taxim (11:23)\/Baldheaded End of a Broom (03:14)\/Louisiana Man (02:45)\/You Don't Love Me (03:59)\/Beacon from Mars (12:31)\/Rampe Rampe (03:34)\/Nobody (with Kaleidoscope) (02:36)\/Love Games - Single Version (02:30)\/Egyptian Candy - Single Version (03:01)\/Hello Trouble - Single Version (02:06)\/Just a Taste - Single Version (02:14","album_pic":"https:\/\/i.scdn.co\/image\/ab67616d00001e02614abdd4f4e0f82b90da8120","genres":"Psychedelic Rock\/Acid Rock\/Psychedelic Pop","count":14,"maiuscule":"K"},{"artist":"Kaleidoscope","track":"Taxim","album_name":"A Beacon From Mars (Expanded Edition)","album_type":"Album","album_date":"1968-06-01","album_tracks":"I Found Out (02:10)\/Greenwood Sidee (04:16)\/Life Will Pass You By (03:25)\/Taxim (11:23)\/Baldheaded End of a Broom (03:14)\/Louisiana Man (02:45)\/You Don't Love Me (03:59)\/Beacon from Mars (12:31)\/Rampe Rampe (03:34)\/Nobody (with Kaleidoscope) (02:36)\/Love Games - Single Version (02:30)\/Egyptian Candy - Single Version (03:01)\/Hello Trouble - Single Version (02:06)\/Just a Taste - Single Version (02:14","album_pic":"https:\/\/i.scdn.co\/image\/ab67616d00001e02614abdd4f4e0f82b90da8120","genres":"Psychedelic Rock\/Acid Rock\/Psychedelic Pop","count":14,"maiuscule":"K"},{"artist":"Kaleidoscope","track":"Beacon from Mars","album_name":"A Beacon From Mars (Expanded Edition)","album_type":"Album","album_date":"1968-06-01","album_tracks":"I Found Out (02:10)\/Greenwood Sidee (04:16)\/Life Will Pass You By (03:25)\/Taxim (11:23)\/Baldheaded End of a Broom (03:14)\/Louisiana Man (02:45)\/You Don't Love Me (03:59)\/Beacon from Mars (12:31)\/Rampe Rampe (03:34)\/Nobody (with Kaleidoscope) (02:36)\/Love Games - Single Version (02:30)\/Egyptian Candy - Single Version (03:01)\/Hello Trouble - Single Version (02:06)\/Just a Taste - Single Version (02:14","album_pic":"https:\/\/i.scdn.co\/image\/ab67616d00001e02614abdd4f4e0f82b90da8120","genres":"Psychedelic Rock\/Acid Rock\/Psychedelic Pop","count":14,"maiuscule":"K"}]